empirical_copula/__init__.py
empirical_copula/plot.py
empirical_copula/significance.py
empirical_copula-1.0.dist-info/LICENSE
empirical_copula-1.0.dist-info/METADATA
empirical_copula-1.0.dist-info/WHEEL
empirical_copula-1.0.dist-info/top_level.txt
empirical_copula-1.0.dist-info/RECORD
